{
  "conduction": {
    "tabs": {
      "tab": {
        "background-color": { "value": "transparent" },
        "color": { "value": "{beek.color.grey.29}" },
        "border-width": {},
        "border-style": {},
        "border-color": {},
        "border-bottom": {},
        "border-bottom-width": { "value": "{beek.size.2xs}" },
        "border-bottom-style": { "value": "solid" },
        "border-bottom-color": { "value": "{beek.color.grey.82}" },
        "bottom": { "value": "-2px" },
        "padding-block-start": { "value": "{beek.size.xs}" },
        "padding-block-end": { "value": "{beek.size.xs}" },
        "padding-inline-start": { "value": "{beek.size.sm}" },
        "padding-inline-end": { "value": "{beek.size.sm}" },
        "margin-inline-end": {},
        "font-size": { "value": "{beek.font-size.md}" },
        "font-weight": { "value": "{beek.typography.font-weight.normal}" },
        "font-family": { "value": "{utrecht.document.font-family}" },
        "max-width": { "value": "unset" },
        "min-width": { "value": "160px" },
        "min-height": { "value": "61px" },
        "letter-spacing": {},
        "text-transform": {},
        "selected": {
          "background-color": { "value": "transparent" },
          "color": { "value": "{beek.color.grey.29}" },
          "box-shadow": {},
          "border-width": {},
          "border-style": {},
          "border-color": {},
          "border-bottom": {},
          "border-bottom-width": { "value": "{beek.size.2xs}" },
          "border-bottom-style": { "value": "solid" },
          "border-bottom-color": { "value": "{beek.color.orange.49}" },
          "font-weight": { "value": "{beek.typography.font-weight.bold}" },
          "font-family": { "value": "{utrecht.document.font-family}" },
          "hover": {
            "background-color": {},
            "color": { "value": "{beek.color.grey.29}" },
            "text-decoration": {}
          }
        },
        "hover": {
          "background-color": {},
          "color": { "value": "{beek.color.grey.29}" },
          "text-decoration": {},
          "font-weight": {}
        },
        "list": {
          "padding-inline-start": { "value": "0px" },
          "margin-block-end": { "value": "0px" },
          "border-bottom-width": { "value": "{beek.size.3xs}" },
          "border-bottom-style": { "value": "solid" },
          "border-bottom-color": { "value": "{beek.color.grey.82}" }
        },
        "panel": {
          "background-color": {},
          "padding-block-start": { "value": "{beek.size.lg}" },
          "padding-block-end": { "value": "{beek.size.lg}" },
          "padding-inline-start": { "value": "{beek.size.lg}" },
          "padding-inline-end": { "value": "{beek.size.lg}" },
          "border-width": {},
          "border-style": {},
          "border-color": {},
          "border-top": {}
        }
      },
      "scroll-button": {
        "background-color": { "value": "{beek.color.primary}" },
        "color": { "value": "{beek.color.white.100}" },
        "border-width": {},
        "border-style": {},
        "border-color": {},
        "hover": {
          "background-color": { "value": "{beek.color.primary-hover}" },
          "color": { "value": "{beek.color.white.100}" }
        }
      }
    }
  }
}
