{
  "utrecht": {
    "form-input": {
      "border-bottom-width": {},
      "border-color": { "value": "{helmond.color.taupe.33}" },
      "border-radius": { "value": "0" },
      "border-width": { "value": "{helmond.size.4xs}" },
      "color": { "value": "{helmond.color.grey.29}" },
      "font-family": { "value": "{helmond.typography.Arial.font-family}" },
      "font-size": {
        "value": "0.938rem",
        "comment": "15px"
      },
      "min-inline-height": {},
      "max-inline-size": {},
      "padding-block-end": { "value": "{helmond.size.xs}" },
      "padding-block-start": { "value": "{helmond.size.xs}" },
      "padding-inline-end": { "value": "{helmond.size.sm}" },
      "padding-inline-start": { "value": "{helmond.size.sm}" },
      "disabled": {
        "border-color": { "value": "{helmond.color.grey.87}" },
        "color": {}
      },
      "invalid": {
        "border-color": { "value": "{helmond.color.error}" },
        "border-width": { "value": "{helmond.size.4xs}" }
      },
      "read-only": {
        "border-color": { "value": "{helmond.color.grey.48}" },
        "color": {}
      }
    }
  }
}
