{
  "utrecht": {
    "skip-link": {
      "background-color": { "value": "{zuiddrecht.color.white.100}" },
      "color": { "value": "{zuiddrecht.color.primary}" },
      "min-block-size": { "value": "20px" },
      "min-inline-size": { "value": "20px" },
      "padding-block-start": { "value": "16px" },
      "padding-block-end": { "value": "16px" },
      "padding-inline-start": { "value": "16px" },
      "padding-inline-end": { "value": "16px" },
      "text-decoration": { "value": "none" },
      "z-index": { "value": "100000" }
    }
  }
}
